{
    "fluentMethods": true,
    "relationships": [
        {
            "relationshipType": "many-to-one",
            "relationshipName": "rate",
            "otherEntityName": "rates",
            "otherEntityField": "id"
        }
    ],
    "fields": [
        {
            "fieldName": "ossPath",
            "javadoc": "图片路径",
            "fieldType": "String",
            "fieldValidateRules": [
                "maxlength"
            ],
            "fieldValidateRulesMaxlength": 1024
        }
    ],
    "changelogDate": "20180614062020",
    "entityTableName": "rates_pics",
    "dto": "mapstruct",
    "pagination": "no",
    "service": "serviceClass",
    "jpaMetamodelFiltering": false,
    "skipClient": true,
    "microserviceName": "pinfan"
}