<?xml version="1.1" encoding="UTF-8" standalone="no"?>
<databaseChangeLog xmlns="http://www.liquibase.org/xml/ns/dbchangelog" xmlns:ext="http://www.liquibase.org/xml/ns/dbchangelog-ext" xmlns:xsi="http://www.w3.org/2001/XMLSchema-instance" xsi:schemaLocation="http://www.liquibase.org/xml/ns/dbchangelog-ext http://www.liquibase.org/xml/ns/dbchangelog/dbchangelog-ext.xsd http://www.liquibase.org/xml/ns/dbchangelog http://www.liquibase.org/xml/ns/dbchangelog/dbchangelog-3.5.xsd">
    <changeSet author="l.mao (generated)" id="1531455332426-1">
        <addColumn tableName="clock_in">
            <column name="activity_id" type="integer"/>
        </addColumn>
    </changeSet>
    <changeSet author="l.mao (generated)" id="1531455332426-2">
        <addColumn tableName="fitness_activity">
            <column name="reading_count" type="integer"/>
        </addColumn>
    </changeSet>
    <changeSet author="l.mao (generated)" id="1531455332426-3">
        <addColumn tableName="pin_fan_activity">
            <column name="reading_count" type="integer"/>
        </addColumn>
    </changeSet>
</databaseChangeLog>
